jira_mcp_server/__init__.py
jira_mcp_server/config.py
jira_mcp_server/jira_client.py
jira_mcp_server/models.py
jira_mcp_server/schema_cache.py
jira_mcp_server/server.py
jira_mcp_server/validators.py
jira_mcp_server/tools/__init__.py
jira_mcp_server/tools/comment_tools.py
jira_mcp_server/tools/filter_tools.py
jira_mcp_server/tools/issue_tools.py
jira_mcp_server/tools/search_tools.py
jira_mcp_server/tools/workflow_tools.py
fastmcp_jira_server-0.6.2.dist-info/METADATA
fastmcp_jira_server-0.6.2.dist-info/WHEEL
fastmcp_jira_server-0.6.2.dist-info/entry_points.txt
fastmcp_jira_server-0.6.2.dist-info/licenses/LICENSE
fastmcp_jira_server-0.6.2.dist-info/RECORD
