Metadata-Version: 2.4
Name: fastmcp-jira-server
Version: 0.6.2
Summary: FastMCP server for self-hosted Jira with full CRUD operations, custom fields, JQL search, filters, workflows, and comments
Project-URL: Homepage, https://github.com/troylar/jira-mcp-server
Project-URL: Documentation, https://github.com/troylar/jira-mcp-server#readme
Project-URL: Repository, https://github.com/troylar/jira-mcp-server
Project-URL: Issues, https://github.com/troylar/jira-mcp-server/issues
Author-email: Troy Larson <troy.larson@gmail.com>
License: MIT
License-File: LICENSE
Keywords: fastmcp,jira,jira-api,jql,mcp,model-context-protocol,self-hosted,workflow
Classifier: Development Status :: 4 - Beta
Classifier: Intended Audience :: Developers
Classifier: License :: OSI Approved :: MIT License
Classifier: Programming Language :: Python :: 3
Classifier: Programming Language :: Python :: 3.10
Classifier: Programming Language :: Python :: 3.11
Classifier: Programming Language :: Python :: 3.12
Classifier: Programming Language :: Python :: 3.13
Classifier: Topic :: Office/Business
Classifier: Topic :: Software Development :: Libraries :: Python Modules
Requires-Python: >=3.10
Requires-Dist: fastmcp>=0.1.0
Requires-Dist: httpx>=0.25.0
Requires-Dist: pydantic-settings>=2.0.0
Requires-Dist: pydantic>=2.0.0
Provides-Extra: dev
Requires-Dist: black>=23.0.0; extra == 'dev'
Requires-Dist: hatch; extra == 'dev'
Requires-Dist: mypy>=1.0.0; extra == 'dev'
Requires-Dist: pytest-asyncio>=0.21.0; extra == 'dev'
Requires-Dist: pytest-cov>=4.0.0; extra == 'dev'
Requires-Dist: pytest-mock>=3.10.0; extra == 'dev'
Requires-Dist: pytest>=7.0.0; extra == 'dev'
Requires-Dist: responses>=0.22.0; extra == 'dev'
Requires-Dist: ruff>=0.1.0; extra == 'dev'
